mongolian_to_ipa/__init__.py
mongolian_to_ipa/char_convertor.py
mongolian_to_ipa/helpers.py
mongolian_to_ipa/mongolia_ipa_dictionary.py
mongolian2ipa-0.0.1.dist-info/METADATA
mongolian2ipa-0.0.1.dist-info/WHEEL
mongolian2ipa-0.0.1.dist-info/top_level.txt
mongolian2ipa-0.0.1.dist-info/RECORD
